{"package":"zanshin",
 "description":"to-do list manager",
 "details":" Zanshin is a powerful yet simple application for managing your day to day\n actions and notes. It helps you organize and reduce the cognitive pressure of\n what one has to do in his job and personal life. You'll never forget anything\n anymore, getting your mind like water.\n",
 "installedSize":"1129",
 "downloadSize":"404940",
 "homepage":"http:\/\/zanshin.kde.org\/",
 "bugs":null,"screenshots":["http:\/\/placehold.it\/120x90",
 "http:\/\/placehold.it\/120x90",
 "http:\/\/placehold.it\/120x90"]}